MANIFEST.in
README.txt
setup.py
docs/HISTORY.txt
smitheme/__init__.py
smitheme/__init__.pyc
smitheme.bclear.egg-info/PKG-INFO
smitheme.bclear.egg-info/SOURCES.txt
smitheme.bclear.egg-info/dependency_links.txt
smitheme.bclear.egg-info/namespace_packages.txt
smitheme.bclear.egg-info/requires.txt
smitheme.bclear.egg-info/top_level.txt
smitheme.bclear.egg-info/zip-safe
smitheme/bclear/__init__.py
smitheme/bclear/__init__.pyc
smitheme/bclear/configure.zcml
smitheme/bclear/skin.py
smitheme/bclear/skin.pyc
smitheme/bclear/smi.py
smitheme/bclear/smi.pyc
smitheme/bclear/smi_templates/smifooter.pt
smitheme/bclear/smi_templates/smipathbar.pt
smitheme/bclear/static/bclear.css
smitheme/bclear/static/calendar.png
smitheme/bclear/static/edit.png
smitheme/bclear/static/jquery.smi.js
smitheme/bclear/static/list-add.png
smitheme/bclear/static/list-remove.png
smitheme/bclear/static/magnifier.png
smitheme/bclear/static/overlay.png
smitheme/bclear/static/reset.css
smitheme/bclear/static/slideleft.gif
smitheme/bclear/static/slideright.gif
smitheme/bclear/static/user.png