Metadata-Version: 1.0
Name: smitheme.bclear
Version: 1.0.8
Summary: Bethel's SMI Theme / Skin
Home-page: UNKNOWN
Author: Andy Altepeter / Bethel University
Author-email: aaltepet@bethel.edu
License: GPL
Keywords: python silva theme
Platform: UNKNOWN
Classifier: Programming Language :: Python
Classifier: Topic :: Software Development :: Libraries :: Python Modules
